package/__init__.py
package/example.txt
package/main.py
flame_package_d-0.0.1.dist-info/LICENSE
flame_package_d-0.0.1.dist-info/METADATA
flame_package_d-0.0.1.dist-info/WHEEL
flame_package_d-0.0.1.dist-info/top_level.txt
flame_package_d-0.0.1.dist-info/RECORD
